verskyt/__init__.py
verskyt/py.typed
verskyt/benchmarks/__init__.py
verskyt/benchmarks/xor_suite.py
verskyt/core/__init__.py
verskyt/core/similarity.py
verskyt/interventions/__init__.py
verskyt/interventions/analysis.py
verskyt/interventions/grounding.py
verskyt/interventions/manager.py
verskyt/layers/__init__.py
verskyt/layers/projection.py
verskyt/utils/__init__.py
verskyt/utils/initializers.py
verskyt/visualizations/__init__.py
verskyt/visualizations/plotting.py
verskyt-0.2.4.dist-info/LICENSE
verskyt-0.2.4.dist-info/METADATA
verskyt-0.2.4.dist-info/WHEEL
verskyt-0.2.4.dist-info/top_level.txt
verskyt-0.2.4.dist-info/RECORD
