Metadata-Version: 2.1
Name: verskyt
Version: 0.2.4
Summary: Python library for Tversky Neural Networks with research tools for model introspection and prototype analysis
Author: Jeff Smith
License: MIT
Project-URL: Homepage, https://github.com/jeffreyksmithjr/verskyt
Project-URL: Bug Tracker, https://github.com/jeffreyksmithjr/verskyt/issues
Project-URL: Documentation, https://verskyt.readthedocs.io
Project-URL: Source, https://github.com/jeffreyksmithjr/verskyt
Keywords: deep-learning,neural-networks,tversky,similarity,pytorch,research,interpretability
Classifier: Development Status :: 3 - Alpha
Classifier: Intended Audience :: Science/Research
Classifier: License :: OSI Approved :: MIT License
Classifier: Programming Language :: Python :: 3
Classifier: Programming Language :: Python :: 3.8
Classifier: Programming Language :: Python :: 3.9
Classifier: Programming Language :: Python :: 3.10
Classifier: Programming Language :: Python :: 3.11
Classifier: Topic :: Scientific/Engineering :: Artificial Intelligence
Classifier: Topic :: Scientific/Engineering :: Mathematics
Classifier: Topic :: Software Development :: Libraries :: Python Modules
Requires-Python: >=3.8
License-File: LICENSE
Requires-Dist: torch>=1.10.0
Requires-Dist: numpy>=1.19.0
Requires-Dist: matplotlib>=3.5.0
Requires-Dist: tqdm>=4.62.0
Provides-Extra: benchmarks
Requires-Dist: torchvision>=0.11.0; extra == "benchmarks"
Requires-Dist: scikit-learn>=1.1.0; extra == "benchmarks"
Requires-Dist: pandas>=1.3.0; extra == "benchmarks"
Provides-Extra: dev
Requires-Dist: pytest>=7.0.0; extra == "dev"
Requires-Dist: pytest-cov>=3.0.0; extra == "dev"
Requires-Dist: black>=22.0.0; extra == "dev"
Requires-Dist: isort>=5.10.0; extra == "dev"
Requires-Dist: flake8>=4.0.0; extra == "dev"
Requires-Dist: mypy>=0.950; extra == "dev"
Requires-Dist: pre-commit>=3.0.0; extra == "dev"
Requires-Dist: jupyter>=1.0.0; extra == "dev"
Requires-Dist: torchvision>=0.11.0; extra == "dev"
Requires-Dist: sphinx>=5.0.0; extra == "dev"
Requires-Dist: furo>=2022.6.21; extra == "dev"
Requires-Dist: myst-parser>=0.18.0; extra == "dev"
Requires-Dist: myst-nb>=0.17.0; extra == "dev"
Requires-Dist: sphinx-autodoc-typehints>=1.19.0; extra == "dev"
Requires-Dist: verskyt[visualization]; extra == "dev"
Provides-Extra: visualization
Requires-Dist: matplotlib>=3.5.0; extra == "visualization"
Requires-Dist: seaborn>=0.12.0; extra == "visualization"
Requires-Dist: scikit-learn>=1.1.0; extra == "visualization"
